fyle_internals/bootstrap.py
fyle_internals/receiver.py
fyle_internals/sender.py
fylecli-0.0.5.data/scripts/fylecli.py
fylecli-0.0.5.dist-info/LICENSE
fylecli-0.0.5.dist-info/METADATA
fylecli-0.0.5.dist-info/WHEEL
fylecli-0.0.5.dist-info/top_level.txt
fylecli-0.0.5.dist-info/RECORD
