Metadata-Version: 2.1
Name: fylecli
Version: 0.0.5
Summary: File transfer
Author: Mark Smirnov
Author-email: Mark Smirnov <mark@mark99.ru>
Platform: any
Classifier: Programming Language :: Python :: 3
Classifier: License :: OSI Approved :: MIT License
Classifier: Operating System :: OS Independent
Requires-Python: >=3.9
License-File: LICENSE
Requires-Dist: websockets
Requires-Dist: requests
